aicoe/hello_world/__init__.py
aicoe/hello_world/cli.py
aicoe_hello_world-0.0.3.dist-info/METADATA
aicoe_hello_world-0.0.3.dist-info/RECORD
aicoe_hello_world-0.0.3.dist-info/WHEEL
aicoe_hello_world-0.0.3.dist-info/top_level.txt
