Metadata-Version: 2.1
Name: aicoe-hello-world
Version: 0.0.3
Summary: Hello World module of AICoE
Home-page: UNKNOWN
Author: Harshad Reddy Nalla
Author-email: hnalla@redhat.com
License: GPLv3+
Platform: UNKNOWN
Requires-Dist: click
